{
  "id": "0d47c3c84a76",
  "title": "‘Godman’ Kharat Held in 8th Abuse Case, Sent to Jail as Remand Denied",
  "description": "The eighth case related to Kharat allegedly sexually exploiting a woman who had approached him in search of solutions to her family problems, according to police.",
  "link": "https://www.deccanchronicle.com/nation/godman-kharat-held-in-8th-abuse-case-sent-to-jail-as-remand-denied-1953780",
  "date": "2026-04-30",
  "source_id": "deccan_chronicle",
  "source_name": "Deccan Chronicle",
  "source_short": "DC",
  "sectors": [
    "Digital & Technology",
    "Health"
  ],
  "sector_slugs": [
    "digital-technology",
    "health"
  ],
  "type": "policy",
  "level": "central",
  "state": ""
}