{
  "id": "12d1bbb4633d",
  "title": "AP Signs MoU with Indian Culinary Institute to Promote Culinary Tourism",
  "description": "The MoU was exchanged between representatives of the Indian Culinary Institute and Special Chief Secretary (Tourism) Ajay Jain in the presence of Chief Minister N Chandrababu Naidu",
  "link": "https://www.deccanchronicle.com/southern-states/andhra-pradesh/ap-signs-mou-with-indian-culinary-institute-to-promote-culinary-tourism-1946373",
  "date": "2026-03-26",
  "source_id": "deccan_chronicle",
  "source_name": "Deccan Chronicle",
  "source_short": "DC",
  "sectors": [
    "Digital & Technology",
    "Social Protection"
  ],
  "sector_slugs": [
    "digital-technology",
    "social-protection"
  ],
  "type": "policy",
  "level": "central",
  "state": ""
}