{
  "id": "139a301d7da7",
  "title": "Supreme Court refuses to entertain pleas of those on election duty in Bengal, asks them to move tribunal",
  "description": "The apex Court asked them to approach the appellate tribunals constituted to decide appeals against the deletion or exclusion of names from the voter list",
  "link": "https://www.thehindu.com/elections/west-bengal-assembly/supreme-court-refuses-to-entertain-pleas-of-those-on-election-duty-in-bengal-asks-them-to-move-tribunal/article70901149.ece",
  "date": "2026-04-24",
  "source_id": "the_hindu_policy",
  "source_name": "The Hindu - National",
  "source_short": "The Hindu",
  "sectors": [
    "Digital & Technology",
    "Social Protection",
    "Governance & Reform"
  ],
  "sector_slugs": [
    "digital-technology",
    "social-protection",
    "governance-reform"
  ],
  "type": "policy",
  "level": "central",
  "state": ""
}