{
  "id": "1b69684a4dbd",
  "title": "Venus-Jupiter conjunction: Nehru Planetarium to host special viewing on June 9",
  "description": "Venus-Jupiter conjunction: Nehru Planetarium to host special viewing on June 9",
  "link": "https://www.hindustantimes.com/india-news/venusjupiter-conjunction-nehru-planetarium-to-host-special-viewing-on-june-9-101780747540584.html",
  "date": "2026-06-06",
  "source_id": "hindustan_times",
  "source_name": "Hindustan Times - India",
  "source_short": "HT",
  "sectors": [
    "Digital & Technology",
    "Social Protection"
  ],
  "sector_slugs": [
    "digital-technology",
    "social-protection"
  ],
  "type": "policy",
  "level": "media",
  "state": "",
  "first_seen": "2026-06-06"
}