{
  "id": "1efd55cf99e2",
  "title": "KMC Hikes Charges Across The Board; Build Plan Approval Goes Up 3 Times",
  "description": "Kakinada civic body hikes fees for building plans, trade licences",
  "link": "https://www.deccanchronicle.com/southern-states/andhra-pradesh/kmc-hikes-charges-across-the-board-build-plan-approval-goes-up-3-times-1948597",
  "date": "2026-04-04",
  "source_id": "deccan_chronicle",
  "source_name": "Deccan Chronicle",
  "source_short": "DC",
  "sectors": [
    "Trade & Commerce"
  ],
  "sector_slugs": [
    "trade-commerce"
  ],
  "type": "policy",
  "level": "central",
  "state": ""
}