{
  "id": "26472c4e48dc",
  "title": "Thirupparankundram, where hillock, temple are in the thick of controversy",
  "description": "NTK’s T. Sathyadevi, Puthiya Tamilagam’s A. Sethuraman, and TVK’s R. Nirmalkumar are adding to the otherwise straight fight between V.V. Rajan Chellappa of the AIADMK and Kiruthiga Thangapandi of the DMK",
  "link": "https://www.thehindu.com/elections/tamil-nadu-assembly/thirupparankundram-where-hillock-temple-are-in-the-thick-of-controversy/article70877875.ece",
  "date": "2026-04-21",
  "source_id": "the_hindu_policy",
  "source_name": "The Hindu - National",
  "source_short": "The Hindu",
  "sectors": [
    "Digital & Technology",
    "Social Protection",
    "Energy"
  ],
  "sector_slugs": [
    "digital-technology",
    "social-protection",
    "energy"
  ],
  "type": "policy",
  "level": "central",
  "state": ""
}