{
  "id": "28292e029e4b",
  "title": "IIT Bombay Opens Admission Guidance Session For JEE Advanced Qualifiers",
  "description": "IIT Bombay Open House For JEE Advanced Qualifiers: According to IIT Bombay, the Open House will be conducted on June 7 in webinar mode from 10AM to 1PM and will feature a panel comprising faculty members and current students.",
  "link": "https://www.ndtv.com/education/iit-bombay-to-hold-online-open-house-for-jee-advanced-qualifiers-on-june-7-11594478#publisher=newsstand",
  "date": "2026-06-05",
  "source_id": "ndtv_india",
  "source_name": "NDTV - India",
  "source_short": "NDTV",
  "sectors": [
    "Education",
    "Digital & Technology",
    "Social Protection"
  ],
  "sector_slugs": [
    "education",
    "digital-technology",
    "social-protection"
  ],
  "type": "scheme",
  "level": "media",
  "state": "",
  "first_seen": "2026-06-05"
}