{
  "id": "399080368d81",
  "title": "Alia Bhatt cheers for Dhurandhar 2, calls Ranveer Singh-Aditya Dhar magic in sync",
  "description": "Alia Bhatt cheers for Dhurandhar calls Ranveer SinghAditya Dhar magic in sync",
  "link": "https://www.indiatoday.in/movies/celebrities/story/alia-bhatt-cheers-for-dhurandhar-2-calls-ranveer-singh-aditya-dhar-magic-in-sync-2885643-2026-03-22?utm_source=rss",
  "date": "2026-03-22",
  "source_id": "india_today",
  "source_name": "India Today",
  "source_short": "IndiaToday",
  "sectors": [
    "Digital & Technology"
  ],
  "sector_slugs": [
    "digital-technology"
  ],
  "type": "policy",
  "level": "central",
  "state": ""
}