{
  "id": "3df53ae134e9",
  "title": "Lok Sabha Informed About Centre Cracking Down on Offshore Gaming",
  "description": "The new law prohibits online money gaming and restricts related financial transactions and advertisements, while enforcing 28 per cent GST.",
  "link": "https://www.deccanchronicle.com/southern-states/andhra-pradesh/lok-sabha-informed-about-centre-cracking-down-on-offshore-gaming-1947932",
  "date": "2026-04-01",
  "source_id": "deccan_chronicle",
  "source_name": "Deccan Chronicle",
  "source_short": "DC",
  "sectors": [
    "Digital & Technology",
    "Finance & Economy",
    "Social Protection"
  ],
  "sector_slugs": [
    "digital-technology",
    "finance-economy",
    "social-protection"
  ],
  "type": "policy",
  "level": "central",
  "state": ""
}