{
  "id": "486c55135203",
  "title": "Consolidated voters’ list of 9 States and 3 UTs that underwent SIR Phase II trimmed by 10.2%",
  "description": "Uttar Pradesh records highest net deletion of voters in absolute numbers at 2.04 crore while Lakshadweep sees lowest at 181.",
  "link": "https://www.thehindu.com/news/national/consolidated-voters-list-of-9-states-and-3-uts-that-underwent-sir-phase-ii-trimmed-by-102/article70853877.ece",
  "date": "2026-04-13",
  "source_id": "the_hindu_policy",
  "source_name": "The Hindu - National",
  "source_short": "The Hindu",
  "sectors": [
    "Social Protection"
  ],
  "sector_slugs": [
    "social-protection"
  ],
  "type": "policy",
  "level": "central",
  "state": ""
}