{
  "id": "4ad2c7bf645d",
  "title": "Kerala Weather Update: IMD issues yellow alert; Kerala braces for ‘hot and humid’ week",
  "description": "",
  "link": "https://indianexpress.com/article/india/kerala-weather-update-imd-issues-yellow-alert-kerala-braces-for-hot-and-humid-week-10597859/",
  "date": "2026-03-24",
  "source_id": "indian_express_policy",
  "source_name": "Indian Express - India",
  "source_short": "IE",
  "sectors": [
    "Governance & Reform"
  ],
  "sector_slugs": [
    "governance-reform"
  ],
  "type": "policy",
  "level": "central",
  "state": ""
}