{
  "id": "506e58bd460f",
  "title": "Not road rage, previous night’s bar brawl led to shootout that killed retired Brigadier on morning walk: Dehradun police",
  "description": "",
  "link": "https://indianexpress.com/article/india/not-road-rage-previous-nights-bar-brawl-led-to-shootout-that-killed-retired-brigadier-on-morning-walk-dehradun-police-10610360/",
  "date": "2026-03-31",
  "source_id": "indian_express_policy",
  "source_name": "Indian Express - India",
  "source_short": "IE",
  "sectors": [
    "Energy",
    "Transport & Infrastructure"
  ],
  "sector_slugs": [
    "energy",
    "transport-infrastructure"
  ],
  "type": "policy",
  "level": "central",
  "state": ""
}