{
  "id": "59d67741831f",
  "title": "Crowds Gather at Velankanni Church for Actor-Politician Vijay",
  "description": "Vijay has been visiting various spiritual sites ahead of the election results on May 4.",
  "link": "https://www.deccanchronicle.com/entertainment/kollywood/crowds-gather-at-velankanni-church-for-actor-politician-vijay-1954158",
  "date": "2026-05-02",
  "source_id": "deccan_chronicle",
  "source_name": "Deccan Chronicle",
  "source_short": "DC",
  "sectors": [
    "Digital & Technology",
    "Energy"
  ],
  "sector_slugs": [
    "digital-technology",
    "energy"
  ],
  "type": "policy",
  "level": "central",
  "state": ""
}