{
  "id": "5b807e099ac7",
  "title": "International flights from Navi Mumbai delayed, expansion plans on track: Senior executive",
  "description": "Domestic flights at Navi Mumbai began last Christmas and frequency has now increased to 156 services daily",
  "link": "https://www.thehindubusinessline.com/economy/international-flights-from-navi-mumbai-delayedexpansion-plans-on-track-senior-executive/article70897306.ece",
  "date": "2026-04-23",
  "source_id": "business_line",
  "source_name": "BusinessLine - Economy",
  "source_short": "BL",
  "sectors": [
    "Digital & Technology",
    "Social Protection"
  ],
  "sector_slugs": [
    "digital-technology",
    "social-protection"
  ],
  "type": "policy",
  "level": "central",
  "state": ""
}