{
  "id": "5bbbb5562424",
  "title": "6,046 booked for using mobile phones while driving in week-long operation",
  "description": "",
  "link": "https://www.thehindu.com/news/national/telangana/6046-booked-for-using-mobile-phones-while-driving-in-week-long-operation/article70847718.ece",
  "date": "2026-04-10",
  "source_id": "the_hindu_policy",
  "source_name": "The Hindu - National",
  "source_short": "The Hindu",
  "sectors": [
    "Social Protection"
  ],
  "sector_slugs": [
    "social-protection"
  ],
  "type": "policy",
  "level": "central",
  "state": ""
}