{
  "id": "5ff0947973f1",
  "title": "Integrate resilience in infra projects at design stage & not only after disaster, says Economic Affairs Secretary Anuradha Thakur",
  "description": "",
  "link": "https://indianexpress.com/article/business/integrate-resilience-in-infra-projects-at-design-stage-not-only-after-disaster-dea-secretary-10650866/",
  "date": "2026-04-22",
  "source_id": "indian_express_business",
  "source_name": "Indian Express - Business",
  "source_short": "IE Biz",
  "sectors": [
    "Digital & Technology",
    "Social Protection",
    "Labour & Employment"
  ],
  "sector_slugs": [
    "digital-technology",
    "social-protection",
    "labour-employment"
  ],
  "type": "policy",
  "level": "central",
  "state": ""
}