{
  "id": "6393986d8287",
  "title": "The Exact Method Illegal Online Betting Networks Use To Cash In On IPL",
  "description": "From Telegram links and WhatsApp forwards to direct promotional calls, betting platforms are aggressively targeting users during the IPL season, luring them in with bonus offers, referral schemes and easy sign-ups",
  "link": "https://www.ndtv.com/india-news/inside-the-shadow-economy-riding-ipl-online-betting-networks-11560908#publisher=newsstand",
  "date": "2026-05-28",
  "source_id": "ndtv_india",
  "source_name": "NDTV - India",
  "source_short": "NDTV",
  "sectors": [
    "Digital & Technology",
    "Social Protection",
    "Rural Development"
  ],
  "sector_slugs": [
    "digital-technology",
    "social-protection",
    "rural-development"
  ],
  "type": "legislation",
  "level": "media",
  "state": "",
  "first_seen": "2026-05-29"
}