{
  "id": "69c5f58172b5",
  "title": "Google announces water, skilling, fishing-community programmes around Vizag AI hub",
  "description": "Alongside the data centre, the company has tied up with five partners on watershed management, GPS for fisherfolk, women’s livelihoods and skills training, with the stated aim of preparing local talent for the hub",
  "link": "https://www.thehindu.com/news/cities/Visakhapatnam/google-announces-water-skilling-fishing-community-programmes-around-vizag-ai-hub/article70915334.ece",
  "date": "2026-04-28",
  "source_id": "the_hindu_policy",
  "source_name": "The Hindu - National",
  "source_short": "The Hindu",
  "sectors": [
    "Digital & Technology",
    "Water & Sanitation",
    "Social Protection"
  ],
  "sector_slugs": [
    "digital-technology",
    "water-sanitation",
    "social-protection"
  ],
  "type": "scheme",
  "level": "central",
  "state": ""
}