{
  "id": "6f1876b2676e",
  "title": "Sucheta Dalal moves Delhi court against ban on media reports linking Manoj Sandesara to Sterling Biotech fraud",
  "description": "Journalist Sucheta Dalal has moved a Delhi court challenging the order banning any news content linking Manoj Kesari Chand Sandesara or his family members to the alleged Sterling Biotech bank fraud case. District Judge Vinod Kumar Meena of the Tis Hazari Courts heard the matter on April 13 and issued notice to Manoj Sandesara, Google and Meta. The case will be heard next on April 29.Dalal’s Moneywise Media LLP – which runs Moneylife magazine and digital news portal – has challenged the",
  "link": "https://www.barandbench.com/news/sucheta-dalal-moves-delhi-court-against-ban-on-media-reports-linking-manoj-sandesara-to-sterling-biotech-fraud",
  "date": "2026-04-14",
  "source_id": "barandbench",
  "source_name": "Bar and Bench",
  "source_short": "Bar&Bench",
  "sectors": [
    "Digital & Technology",
    "Social Protection",
    "Transport & Infrastructure"
  ],
  "sector_slugs": [
    "digital-technology",
    "social-protection",
    "transport-infrastructure"
  ],
  "type": "notification",
  "level": "central",
  "state": ""
}