{
  "id": "738842ec2af7",
  "title": "Meta Chief Zuckerberg Doubles Down on AI Spending",
  "description": "The social networking colossus raised its capital expenditures for this year to a range of $125 billion to $145 billion without laying out exactly how that investment would translate into profit.",
  "link": "https://www.deccanchronicle.com/technology/meta-chief-zuckerberg-doubles-down-on-ai-spending-1953720",
  "date": "2026-04-30",
  "source_id": "deccan_chronicle",
  "source_name": "Deccan Chronicle",
  "source_short": "DC",
  "sectors": [
    "Digital & Technology",
    "Finance & Economy",
    "Social Protection"
  ],
  "sector_slugs": [
    "digital-technology",
    "finance-economy",
    "social-protection"
  ],
  "type": "legislation",
  "level": "central",
  "state": ""
}