{
  "id": "7fcceeed81f7",
  "title": "Delhi HC Refers ‘Tridev’ Song Row in Dhurandhar 2 to Mediation",
  "description": "Trimurti Films alleged that Dhurandhar 2's track \"Rang De Lal (Oye Oye)\" used Tridev's track \"Tirchi Topi Wale\" without due authorisation.",
  "link": "https://www.deccanchronicle.com/entertainment/delhi-hc-refers-tridev-song-row-in-dhurandhar-2-to-mediation-1949517",
  "date": "2026-04-09",
  "source_id": "deccan_chronicle",
  "source_name": "Deccan Chronicle",
  "source_short": "DC",
  "sectors": [
    "Digital & Technology",
    "Energy",
    "Governance & Reform"
  ],
  "sector_slugs": [
    "digital-technology",
    "energy",
    "governance-reform"
  ],
  "type": "policy",
  "level": "central",
  "state": ""
}