{
  "id": "832170b97568",
  "title": "Abhijeet Dipke's first words to supporters upon India arrival from US | Watch",
  "description": "Before joining the protest, Abhijeet Dipke landed at Delhi's Indira Gandhi International (IGI) airport on Saturday morning, arriving from the US.",
  "link": "https://www.hindustantimes.com/india-news/abhijeet-dipkes-first-words-to-supporters-upon-india-arrival-from-us-watch-cjp-cockroach-janta-party-101780729627777.html",
  "date": "2026-06-06",
  "source_id": "hindustan_times",
  "source_name": "Hindustan Times - India",
  "source_short": "HT",
  "sectors": [
    "Transport & Infrastructure",
    "Digital & Technology",
    "Social Protection"
  ],
  "sector_slugs": [
    "transport-infrastructure",
    "digital-technology",
    "social-protection"
  ],
  "type": "policy",
  "level": "media",
  "state": "",
  "first_seen": "2026-06-06"
}