{
  "id": "856a5ae1927d",
  "title": "Court denies bail to woman accused in TCS Nashik case",
  "description": "The accused is now likely to appeal against the decision in the Bombay High Court. Four others arrested in the case have been remanded to police custody till May 5",
  "link": "https://www.thehindu.com/news/national/court-denies-bail-to-woman-accused-in-tcs-nashik-case/article70932944.ece",
  "date": "2026-05-03",
  "source_id": "the_hindu_policy",
  "source_name": "The Hindu - National",
  "source_short": "The Hindu",
  "sectors": [
    "Digital & Technology",
    "Social Protection",
    "Energy"
  ],
  "sector_slugs": [
    "digital-technology",
    "social-protection",
    "energy"
  ],
  "type": "policy",
  "level": "central",
  "state": ""
}