{
  "id": "8eb8347d35f5",
  "title": "Woman killed by partner, his associates in Bihar for refusing to engage in sexual acts with others",
  "description": "",
  "link": "https://indianexpress.com/article/india/purnea-murder-case-woman-killed-resisting-assault-bihar-10594303/",
  "date": "2026-03-21",
  "source_id": "indian_express_policy",
  "source_name": "Indian Express - India",
  "source_short": "IE",
  "sectors": [
    "Digital & Technology",
    "Energy"
  ],
  "sector_slugs": [
    "digital-technology",
    "energy"
  ],
  "type": "policy",
  "level": "central",
  "state": ""
}