{
  "id": "900dc3f7389b",
  "title": "CMDA holds stakeholder meeting on online building planning system",
  "description": "CMDA convenes stakeholders to enhance Chennai’s online building planning system, focusing on efficiency and user interface improvements",
  "link": "https://www.thehindu.com/news/cities/chennai/cmda-holds-stakeholder-meeting-on-online-building-planning-system/article71070821.ece",
  "date": "2026-06-07",
  "source_id": "the_hindu_policy",
  "source_name": "The Hindu - National",
  "source_short": "The Hindu",
  "sectors": [
    "Health",
    "Digital & Technology",
    "Social Protection"
  ],
  "sector_slugs": [
    "health",
    "digital-technology",
    "social-protection"
  ],
  "type": "policy",
  "level": "media",
  "state": "",
  "first_seen": "2026-06-07"
}