{
  "id": "92342006c71e",
  "title": "Investing in early childhood mental health support systems is not just a social priority, but an economic necessity: MP",
  "description": "Dakshina Kannada MP Captain Brijesh Chowta expressed need of a clear referral pathways to specialised care for children, where it was required",
  "link": "https://www.thehindu.com/news/cities/Mangalore/investing-in-early-childhood-mental-health-support-systems-is-not-just-a-social-priority-but-an-economic-necessity-mp/article70805699.ece",
  "date": "2026-03-31",
  "source_id": "the_hindu_policy",
  "source_name": "The Hindu - National",
  "source_short": "The Hindu",
  "sectors": [
    "Health",
    "Digital & Technology",
    "Child Rights & Youth"
  ],
  "sector_slugs": [
    "health",
    "digital-technology",
    "child-rights-youth"
  ],
  "type": "policy",
  "level": "central",
  "state": ""
}