{
  "id": "9336198fddfc",
  "title": "From Mumbai’s kitchen to Ladakh’s yak farms, India’s artisanal cheese goes global in Brazil",
  "description": "India’s artisanal cheese shines globally, with Mumbai’s start-up and Ladakh’s tradition winning accolades at Brazil’s cheese competition.",
  "link": "https://www.thehindubusinessline.com/news/from-mumbais-kitchen-to-ladakhs-yak-farms-indias-artisanal-cheese-goes-global-in-brazil/article70897168.ece",
  "date": "2026-04-24",
  "source_id": "business_line",
  "source_name": "BusinessLine - Economy",
  "source_short": "BL",
  "sectors": [
    "Digital & Technology",
    "Social Protection",
    "Governance & Reform"
  ],
  "sector_slugs": [
    "digital-technology",
    "social-protection",
    "governance-reform"
  ],
  "type": "policy",
  "level": "central",
  "state": ""
}