{
  "id": "95ff003bbd2d",
  "title": "GGHs in A.P. told to submit reports on biomedical waste management",
  "description": "The instructions come after a dog fled with an amputated limb from the Government General Hospital premises in Vijayawada",
  "link": "https://www.thehindu.com/news/national/andhra-pradesh/gghs-in-ap-told-to-submit-reports-on-biomedical-waste-management/article70988046.ece",
  "date": "2026-05-16",
  "source_id": "the_hindu_policy",
  "source_name": "The Hindu - National",
  "source_short": "The Hindu",
  "sectors": [
    "Health",
    "Climate & Environment",
    "Digital & Technology"
  ],
  "sector_slugs": [
    "health",
    "climate-environment",
    "digital-technology"
  ],
  "type": "research",
  "level": "media",
  "state": "",
  "first_seen": "2026-05-16"
}