{
  "id": "986eb86f7bf6",
  "title": "Private jet market defies Iran war gloom as rich flock to Monaco GP, Cannes",
  "description": "“The world is in turmoil, but not our passengers,” said Deniz Weissenborn, owner of Platoon Aviation, which charters eight-seat jets, noting that its wealthy clients can handle higher prices",
  "link": "https://www.thehindubusinessline.com/economy/logistics/private-jet-market-defies-iran-war-gloom-as-rich-flock-to-monaco-gp-cannes/article71075610.ece",
  "date": "2026-06-08",
  "source_id": "business_line",
  "source_name": "BusinessLine - Economy",
  "source_short": "BL",
  "sectors": [
    "Digital & Technology",
    "Transport & Infrastructure"
  ],
  "sector_slugs": [
    "digital-technology",
    "transport-infrastructure"
  ],
  "type": "policy",
  "level": "central",
  "state": "",
  "first_seen": "2026-06-08"
}