{
  "id": "98883dca7c30",
  "title": "West Bengal election results updates: Result on final seat awaited, as BJP crosses majority mark",
  "description": "Not only has the BJP been able to hold its strongholds of north Bengal and southwest Bengal but made significant inroads in erstwhile Trinamool bastions of Kolkata and adjoining district.",
  "link": "https://www.thehindu.com/elections/west-bengal-assembly/west-bengal-election-results-live-updates-may-4-2026/article70934929.ece",
  "date": "2026-05-05",
  "source_id": "the_hindu_policy",
  "source_name": "The Hindu - National",
  "source_short": "The Hindu",
  "sectors": [
    "Digital & Technology",
    "Social Protection",
    "Energy"
  ],
  "sector_slugs": [
    "digital-technology",
    "social-protection",
    "energy"
  ],
  "type": "policy",
  "level": "central",
  "state": ""
}