{
  "id": "9a3e6f657433",
  "title": "Union Home Minister and Minister of Cooperation Shri Amit Shah hails passage of Jan V...",
  "description": "Government of India press release: Union Home Minister and Minister of Cooperation Shri Amit Shah hails passage of Jan V...",
  "link": "https://pib.gov.in/PressReleaseDetail.aspx?PRID=2248733",
  "date": "2026-04-03",
  "source_id": "pib",
  "source_name": "Press Information Bureau",
  "source_short": "PIB",
  "sectors": [
    "Digital & Technology",
    "Social Protection"
  ],
  "sector_slugs": [
    "digital-technology",
    "social-protection"
  ],
  "type": "announcement",
  "level": "central",
  "state": ""
}