{
  "id": "a233dad3e157",
  "title": "ICSE, ISC results 2026: How to check?",
  "description": "Students can access the official CISCE websites for downloading the scorecards.",
  "link": "https://www.thehindu.com/education/schools/cisce-icse-isc-results-2026-how-to-check/article70923321.ece",
  "date": "2026-04-30",
  "source_id": "the_hindu_policy",
  "source_name": "The Hindu - National",
  "source_short": "The Hindu",
  "sectors": [
    "Social Protection",
    "Education",
    "Digital & Technology"
  ],
  "sector_slugs": [
    "social-protection",
    "education",
    "digital-technology"
  ],
  "type": "policy",
  "level": "central",
  "state": ""
}