{
  "id": "abcd4130651d",
  "title": "Amarnath Yatra 2026: Amit Shah chairs meeting to review security preparedness",
  "description": "Police have also launched the QR-based “Pahchan App”, designed to digitally verify workers and vendors operating along the yatra route",
  "link": "https://www.thehindu.com/news/national/amarnath-yatra-2026-amit-shah-chairs-meeting-to-review-security-preparedness/article71092768.ece",
  "date": "2026-06-12",
  "source_id": "the_hindu_policy",
  "source_name": "The Hindu - National",
  "source_short": "The Hindu",
  "sectors": [
    "Digital & Technology",
    "Energy",
    "Labour & Employment"
  ],
  "sector_slugs": [
    "digital-technology",
    "energy",
    "labour-employment"
  ],
  "type": "policy",
  "level": "media",
  "state": "",
  "first_seen": "2026-06-12"
}