{
  "id": "accac6667adc",
  "title": "'PM also supervised NEET leak': Rahul Gandhi jabs Modi, BJP asks him to avoid ‘absurd’ statements",
  "description": "The Supreme Court was informed on Friday that PM Modi was personally monitoring concerns regarding the cancellation of NEET-UG.",
  "link": "https://www.hindustantimes.com/india-news/modi-also-supervised-neet-leak-rahul-gandhi-jabs-pm-after-govt-submissions-to-supreme-court-bjp-reacts-101780113039956.html",
  "date": "2026-05-30",
  "source_id": "hindustan_times",
  "source_name": "Hindustan Times - India",
  "source_short": "HT",
  "sectors": [
    "Digital & Technology",
    "Social Protection",
    "Governance & Reform"
  ],
  "sector_slugs": [
    "digital-technology",
    "social-protection",
    "governance-reform"
  ],
  "type": "announcement",
  "level": "media",
  "state": "",
  "first_seen": "2026-05-30"
}