{
  "id": "afd6209b9598",
  "title": "Tamil Nadu Polls: TVK Chief Vijay to Contest from Perambur, Trichy East",
  "description": "Vijay will be going against DMK's sitting MLA RD Shekar, who will contest from Perambur. He is also pitted against the sitting MLA and DMK candidate Inigo Irudayaraj in Trichy East",
  "link": "https://www.deccanchronicle.com/southern-states/tamil-nadu/tamil-nadu-polls-tvk-chief-vijay-to-contest-from-perambur-trichy-east-1947052",
  "date": "2026-03-29",
  "source_id": "deccan_chronicle",
  "source_name": "Deccan Chronicle",
  "source_short": "DC",
  "sectors": [
    "Digital & Technology",
    "Health",
    "Social Protection"
  ],
  "sector_slugs": [
    "digital-technology",
    "health",
    "social-protection"
  ],
  "type": "policy",
  "level": "central",
  "state": ""
}