{
  "id": "b9d39731c55d",
  "title": "Three Killed as Walls, Shed Collapse Amid Heavy Winds in Mancherial",
  "description": "Eight injured, two critical after separate incidents at procurement centres during unseasonal rain and storm",
  "link": "https://www.deccanchronicle.com/southern-states/telangana/three-killed-as-walls-shed-collapse-amid-heavy-winds-in-mancherial-1954981",
  "date": "",
  "source_id": "deccan_chronicle",
  "source_name": "Deccan Chronicle",
  "source_short": "DC",
  "sectors": [
    "Digital & Technology",
    "Energy",
    "Social Protection"
  ],
  "sector_slugs": [
    "digital-technology",
    "energy",
    "social-protection"
  ],
  "type": "policy",
  "level": "central",
  "state": "",
  "first_seen": "2026-05-08"
}