{
  "id": "bd677aef46df",
  "title": "Didi Rejects Modi's Prediction of Her Defeat",
  "description": "She vows to restore deleted voters' names; Bengal CM warns PM for lecture on fish",
  "link": "https://www.deccanchronicle.com/nation/didi-rejects-modis-prediction-of-her-defeat-1949561",
  "date": "2026-04-09",
  "source_id": "deccan_chronicle",
  "source_name": "Deccan Chronicle",
  "source_short": "DC",
  "sectors": [
    "Social Protection"
  ],
  "sector_slugs": [
    "social-protection"
  ],
  "type": "policy",
  "level": "central",
  "state": ""
}