{
  "id": "be0aea79223e",
  "title": "INDIA bloc meeting begins in New Delhi",
  "description": "Amid disarray, Congress sought to project unity and said that even those skipping it had conveyed their “strong opposition” to the Narendra Modi government’s policies",
  "link": "https://www.thehindu.com/news/national/india-bloc-leaders-meeting-in-new-delhi-on-june-8-updates/article71075577.ece",
  "date": "2026-06-08",
  "source_id": "the_hindu_policy",
  "source_name": "The Hindu - National",
  "source_short": "The Hindu",
  "sectors": [
    "Digital & Technology",
    "Social Protection",
    "Energy"
  ],
  "sector_slugs": [
    "digital-technology",
    "social-protection",
    "energy"
  ],
  "type": "policy",
  "level": "media",
  "state": "",
  "first_seen": "2026-06-08"
}