{
  "id": "c0848846d03a",
  "title": "Post-poll clashes hit West Bengal; TMC claims ‘offices attacked’",
  "description": "Three persons were injured in Mamudpur in Naihati after a BJP worker’s house was allegedly attacked by TMC-backed miscreants.",
  "link": "https://www.hindustantimes.com/india-news/postpoll-clashes-hit-west-bengal-tmc-claims-offices-attacked-101777958015682.html",
  "date": "2026-05-05",
  "source_id": "hindustan_times",
  "source_name": "Hindustan Times - India",
  "source_short": "HT",
  "sectors": [
    "Digital & Technology",
    "Social Protection"
  ],
  "sector_slugs": [
    "digital-technology",
    "social-protection"
  ],
  "type": "policy",
  "level": "central",
  "state": ""
}