{
  "id": "c0f1e71f8b76",
  "title": "‘INDIA bloc will jointly decide response’: J&K CM Omar Abdullah on women’s quota bill and delimitation concerns",
  "description": "He raised concerns about the delimitation exercise, alleging that constituency boundaries had previously been drawn to benefit a particular political party.",
  "link": "https://www.hindustantimes.com/india-news/india-bloc-jointly-decide-response-jammu-and-kashmir-cm-omar-abdullah-women-quota-bill-delimitation-concerns-101776241322040.html",
  "date": "2026-04-15",
  "source_id": "hindustan_times",
  "source_name": "Hindustan Times - India",
  "source_short": "HT",
  "sectors": [
    "Digital & Technology",
    "Energy",
    "Governance & Reform"
  ],
  "sector_slugs": [
    "digital-technology",
    "energy",
    "governance-reform"
  ],
  "type": "legislation",
  "level": "central",
  "state": ""
}