{
  "id": "c5b3eac854a2",
  "title": "Iyers, Christians, Rajus Report Higher Share of Inter-caste Marriages: Telangana Caste Survey Analysis",
  "description": "Inter-caste marriages indicate the weakening of social barriers and signal growing social mobility, especially in terms of individual agency, with women exercising greater freedom in choosing their partners",
  "link": "https://www.deccanchronicle.com/southern-states/telangana/iyers-christians-rajus-report-higher-share-of-inter-caste-marriages-telangana-caste-survey-analysis-1951000",
  "date": "2026-04-17",
  "source_id": "deccan_chronicle",
  "source_name": "Deccan Chronicle",
  "source_short": "DC",
  "sectors": [
    "Digital & Technology",
    "Social Protection",
    "Gender & Women"
  ],
  "sector_slugs": [
    "digital-technology",
    "social-protection",
    "gender-women"
  ],
  "type": "research",
  "level": "central",
  "state": ""
}