{
  "id": "cd77dfe10e87",
  "title": "West Asia conflict hits India’s seafood exports to Gulf nations",
  "description": "Industry sources estimate that exports to West Asia account for around ₹2,000–2,500 crore, constituting roughly 3–4% of India’s total seafood exports",
  "link": "https://www.thehindubusinessline.com/economy/agri-business/west-asia-conflict-hits-indias-seafood-exports-to-gulf-nations/article70873197.ece",
  "date": "2026-04-17",
  "source_id": "business_line",
  "source_name": "BusinessLine - Economy",
  "source_short": "BL",
  "sectors": [
    "Digital & Technology",
    "Social Protection",
    "Transport & Infrastructure"
  ],
  "sector_slugs": [
    "digital-technology",
    "social-protection",
    "transport-infrastructure"
  ],
  "type": "policy",
  "level": "central",
  "state": ""
}