{
  "id": "cd95ed8bf5dd",
  "title": "'India belongs to its people, not a select few': Rahul meets tribal leaders opposing Great Nicobar project",
  "description": "“As I listened to them, one thing became immediately clear: their frustration is not just about a ‘project’. This is about people, their identity, and their right to live with dignity on their own land,” Mr. Gandhi said.",
  "link": "https://www.thehindu.com/news/national/rahul-meets-tribal-leaders-opposing-great-nicobar-project/article70784810.ece",
  "date": "2026-03-26",
  "source_id": "the_hindu_policy",
  "source_name": "The Hindu - National",
  "source_short": "The Hindu",
  "sectors": [
    "Digital & Technology",
    "Social Protection",
    "Tribal & Indigenous"
  ],
  "sector_slugs": [
    "digital-technology",
    "social-protection",
    "tribal-indigenous"
  ],
  "type": "policy",
  "level": "central",
  "state": ""
}