{
  "id": "e058df1e864d",
  "title": "UK Treasury Resists Defense Spending Push in 11th-Hour Talks",
  "description": "The UK Treasury continues to resist a push to speed up an increase in defense spending, just days out from unveiling the country’s long-delayed military investment plan.",
  "link": "https://www.livemint.com/politics/uk-treasury-resists-defense-spending-push-in-11th-hour-talks-11781036681743.html",
  "date": "2026-06-10",
  "source_id": "livemint_policy",
  "source_name": "Livemint - Policy & Politics",
  "source_short": "Livemint",
  "sectors": [
    "Finance & Economy",
    "Defence & Security",
    "Digital & Technology"
  ],
  "sector_slugs": [
    "finance-economy",
    "defence-security",
    "digital-technology"
  ],
  "type": "policy",
  "level": "media",
  "state": "",
  "first_seen": "2026-06-10"
}