{
  "id": "e2ebb0fdc64a",
  "title": "91 Lakh Names Deleted From Bengal Electoral Rolls After Judicial Scrutiny Under SIR",
  "description": "The deletion figures following adjudication in South 24 Parganas district stood at nearly 2.23 lakhs, in Purba Bardhaman district at 2.09 lakhs and in Nadia at 2.98 lakhs, the EC data said",
  "link": "https://www.deccanchronicle.com/nation/politics/91-lakh-names-deleted-from-bengal-electoral-rolls-after-judicial-scrutiny-under-sir-1949055",
  "date": "2026-04-07",
  "source_id": "deccan_chronicle",
  "source_name": "Deccan Chronicle",
  "source_short": "DC",
  "sectors": [
    "Social Protection",
    "Digital & Technology",
    "Governance & Reform"
  ],
  "sector_slugs": [
    "social-protection",
    "digital-technology",
    "governance-reform"
  ],
  "type": "policy",
  "level": "central",
  "state": ""
}