{
  "id": "e4c4a3bf76ec",
  "title": "HPCL, BPCL and IOCL Assure Adequate Fuel Availability in Telangana; Public Urged to Avoid Panic Buying",
  "description": "Government of India press release: HPCL, BPCL and IOCL Assure Adequate Fuel Availability in Telangana; Public Urged to Avoid Panic Buying",
  "link": "https://pib.gov.in/PressReleseDetail.aspx?PRID=2245024",
  "date": "2026-03-26",
  "source_id": "state_pib_assam",
  "source_name": "PIB Guwahati (Northeast)",
  "source_short": "PIB NE",
  "sectors": [
    "Digital & Technology"
  ],
  "sector_slugs": [
    "digital-technology"
  ],
  "type": "announcement",
  "level": "state",
  "state": "Assam"
}