{
  "id": "e907a8f1fd32",
  "title": "Aurobindo Pharma arm ties up with European firm for biosimilars",
  "description": "",
  "link": "https://www.thehindu.com/business/aurobindo-pharma-arm-ties-up-with-european-firm-for-biosimilars/article70785294.ece",
  "date": "2026-03-25",
  "source_id": "the_hindu_business",
  "source_name": "The Hindu - Business",
  "source_short": "The Hindu Biz",
  "sectors": [
    "Health",
    "Digital & Technology"
  ],
  "sector_slugs": [
    "health",
    "digital-technology"
  ],
  "type": "policy",
  "level": "central",
  "state": ""
}