{
  "id": "ebdd03b31623",
  "title": "Kerala polls: ‘Hindu MLA’ remarks by BJP’s Guruvayur candidate land him in trouble with election officials",
  "description": "",
  "link": "https://indianexpress.com/article/india/kerala-polls-hindu-mla-remarks-by-bjps-guruvayur-candidate-land-him-in-trouble-with-election-officials-10595716/",
  "date": "2026-03-23",
  "source_id": "indian_express_policy",
  "source_name": "Indian Express - India",
  "source_short": "IE",
  "sectors": [
    "Digital & Technology"
  ],
  "sector_slugs": [
    "digital-technology"
  ],
  "type": "policy",
  "level": "central",
  "state": ""
}