{
  "id": "f78ea86d570c",
  "title": "No \"Bacterial Infection\" Found In Mumbai Family Watermelon-Deaths",
  "description": "Mumbai hospital report finds no bacterial infection in four family members who died after eating watermelon.",
  "link": "https://www.ndtv.com/india-news/no-bacterial-infection-found-in-mumbai-family-deaths-after-eating-watermelon-11458859#publisher=newsstand",
  "date": "2026-05-07",
  "source_id": "ndtv_india",
  "source_name": "NDTV - India",
  "source_short": "NDTV",
  "sectors": [
    "Health",
    "Digital & Technology",
    "Water & Sanitation"
  ],
  "sector_slugs": [
    "health",
    "digital-technology",
    "water-sanitation"
  ],
  "type": "research",
  "level": "central",
  "state": ""
}