{
  "Child Rights & Youth": 60,
  "Digital & Technology": 1324,
  "Social Protection": 1295,
  "Education": 163,
  "Labour & Employment": 91,
  "Finance & Economy": 195,
  "Energy": 390,
  "Agriculture": 82,
  "Health": 187,
  "Rural Development": 46,
  "Water & Sanitation": 49,
  "Gender & Women": 48,
  "Governance & Reform": 213,
  "Urban Development": 54,
  "Housing": 26,
  "Defence & Security": 67,
  "Climate & Environment": 79,
  "Science & Innovation": 66,
  "Transport & Infrastructure": 166,
  "Tribal & Indigenous": 20,
  "Trade & Commerce": 79,
  "Civil Liberties": 10,
  "Disability & Inclusion": 3
}